ftexplore/__init__.py
ftexplore/__main__.py
ftexplore/module.py
ftexplore/module_caching.py
ftexplore/eventprocessor/__init__.py
ftexplore/eventprocessor/base.py
ftexplore/eventprocessor/standalone.py
ftexplore/eventprocessor/tk.py
ftexplore/gui/__init__.py
ftexplore/gui/ftgui.py
ftexplore/gui/scrolledtext.py
ftexplore/gui/tooltip.py
ftexplore/hardware/__init__.py
ftexplore/hardware/base.py
ftexplore/hardware/builtingpio.py
ftexplore/hardware/demo.py
ftexplore/hardware/didacta.py
ftexplore/hardware/ftduino.py
ftexplore/hardware/motorhat.py
ftexplore/hardware/remote.py
ftexplore/listener/__init__.py
ftexplore/listener/listener.py
ftexplore/usercode/__init__.py
ftexplore/usercode/ftinterface.py
ftexplore/usercode/userfile.py
ftexplore-2.5.0.dist-info/LICENSE.txt
ftexplore-2.5.0.dist-info/METADATA
ftexplore-2.5.0.dist-info/WHEEL
ftexplore-2.5.0.dist-info/top_level.txt
ftexplore-2.5.0.dist-info/RECORD
