Metadata-Version: 2.1
Name: ftexplore
Version: 2.5.0
Summary: ft-Explore allows to control motors and to check inputs by GUI and user-provided Python code
Home-page: https://www.henrici.name/projects/ftexplore.html
Author: Dirk Henrici
Author-email: ftexplore@henrici.name
Project-URL: German Homepage, https://www.henrici.name/projects/ftexplore.html
Project-URL: Repository, https://www.hosting-srv.de/gitea/HNET/ftexplore/
Project-URL: Source, https://www.hosting-srv.de/gitea/HNET/ftexplore/src/branch/master/src
Keywords: motorhat raspberrypi fischertechnik education
Classifier: Programming Language :: Python
Classifier: Programming Language :: Python :: 3
Classifier: License :: OSI Approved :: GNU General Public License v3 or later (GPLv3+)
Classifier: Operating System :: OS Independent
Classifier: Development Status :: 4 - Beta
Classifier: Intended Audience :: Education
Classifier: Intended Audience :: End Users/Desktop
Requires-Python: >=3.5
License-File: LICENSE.txt
Provides-Extra: keyboard
Requires-Dist: keyboard; extra == "keyboard"
Provides-Extra: remote
Requires-Dist: cffi; extra == "remote"
Requires-Dist: pynng; extra == "remote"
Provides-Extra: usb
Requires-Dist: libusb; extra == "usb"
Requires-Dist: pyusb; extra == "usb"
